{
  "nodes": {
    "SitePage /dev-404-page/": {
      "jsonName": "dev-404-page-5f9",
      "internalComponentName": "ComponentDev404Page",
      "path": "/dev-404-page/",
      "component": "/Users/Rurka/dxrs/.cache/dev-404-page.js",
      "componentChunkName": "component---cache-dev-404-page-js",
      "context": {},
      "pluginCreator___NODE": "d48d1c52-fe48-53cb-8f08-aa4b47dde5a5",
      "pluginCreatorId": "d48d1c52-fe48-53cb-8f08-aa4b47dde5a5",
      "componentPath": "/Users/Rurka/dxrs/.cache/dev-404-page.js",
      "id": "SitePage /dev-404-page/",
      "parent": "SOURCE",
      "children": [],
      "internal": {
        "type": "SitePage",
        "contentDigest": "565039bd1cf71addbb540247316dd562",
        "description": "d48d1c52-fe48-53cb-8f08-aa4b47dde5a5",
        "owner": "internal-data-bridge"
      }
    },
    "d48d1c52-fe48-53cb-8f08-aa4b47dde5a5": {
      "resolve": "/Users/Rurka/dxrs/node_modules/gatsby/dist/internal-plugins/dev-404-page",
      "id": "d48d1c52-fe48-53cb-8f08-aa4b47dde5a5",
      "name": "dev-404-page",
      "version": "1.0.0",
      "pluginOptions": {
        "plugins": []
      },
      "nodeAPIs": [
        "createPagesStatefully"
      ],
      "browserAPIs": [],
      "ssrAPIs": [],
      "pluginFilepath": "/Users/Rurka/dxrs/node_modules/gatsby/dist/internal-plugins/dev-404-page",
      "packageJson": {
        "name": "dev-404-page",
        "description": "Internal plugin to add a 404 page in development with helpful information",
        "version": "1.0.0",
        "main": "index.js",
        "author": "Kyle Mathews <mathews.kyle@gmail.com>",
        "license": "MIT",
        "dependencies": [],
        "devDependencies": [],
        "peerDependencies": [],
        "optionalDependecies": [],
        "bundledDependecies": []
      },
      "parent": "SOURCE",
      "children": [],
      "internal": {
        "contentDigest": "debf5533ddf740197db371b4e2d486e3",
        "type": "SitePlugin",
        "owner": "internal-data-bridge"
      }
    },
    "1fc32581-893a-55e8-8927-bcd667e2b700": {
      "resolve": "/Users/Rurka/dxrs/node_modules/gatsby/dist/internal-plugins/load-babel-config",
      "id": "1fc32581-893a-55e8-8927-bcd667e2b700",
      "name": "load-babel-config",
      "version": "1.0.0",
      "pluginOptions": {
        "plugins": []
      },
      "nodeAPIs": [
        "onPreBootstrap"
      ],
      "browserAPIs": [],
      "ssrAPIs": [],
      "pluginFilepath": "/Users/Rurka/dxrs/node_modules/gatsby/dist/internal-plugins/load-babel-config",
      "packageJson": {
        "name": "load-babel-config",
        "description": "Internal plugin that handles loading Babel configs",
        "version": "1.0.0",
        "main": "index.js",
        "author": "Kyle Mathews <mathews.kyle@gmail.com>",
        "license": "MIT",
        "dependencies": [],
        "devDependencies": [],
        "peerDependencies": [],
        "optionalDependecies": [],
        "bundledDependecies": []
      },
      "parent": "SOURCE",
      "children": [],
      "internal": {
        "contentDigest": "84d311fab662ab26281139f6872f7d31",
        "type": "SitePlugin",
        "owner": "internal-data-bridge"
      }
    },
    "a5079d69-ba80-53dc-82f9-0f440bd5448c": {
      "resolve": "/Users/Rurka/dxrs/node_modules/gatsby/dist/internal-plugins/internal-data-bridge",
      "id": "a5079d69-ba80-53dc-82f9-0f440bd5448c",
      "name": "internal-data-bridge",
      "version": "1.0.0",
      "pluginOptions": {
        "plugins": []
      },
      "nodeAPIs": [
        "sourceNodes",
        "onCreatePage"
      ],
      "browserAPIs": [],
      "ssrAPIs": [],
      "pluginFilepath": "/Users/Rurka/dxrs/node_modules/gatsby/dist/internal-plugins/internal-data-bridge",
      "packageJson": {
        "name": "internal-data-bridge",
        "description": "An internal Gatsby plugin which creates data nodes from internal data",
        "version": "1.0.0",
        "main": "index.js",
        "author": "Kyle Mathews <mathews.kyle@gmail.com>",
        "license": "MIT",
        "dependencies": [],
        "devDependencies": [],
        "peerDependencies": [],
        "optionalDependecies": [],
        "bundledDependecies": []
      },
      "parent": "SOURCE",
      "children": [],
      "internal": {
        "contentDigest": "f083c2b6bf7ee3ef4a23bc0e562a93eb",
        "type": "SitePlugin",
        "owner": "internal-data-bridge"
      }
    },
    "f795702c-a3b8-5a88-88ee-5d06019d44fa": {
      "resolve": "/Users/Rurka/dxrs/node_modules/gatsby/dist/internal-plugins/prod-404",
      "id": "f795702c-a3b8-5a88-88ee-5d06019d44fa",
      "name": "prod-404",
      "version": "1.0.0",
      "pluginOptions": {
        "plugins": []
      },
      "nodeAPIs": [
        "onCreatePage"
      ],
      "browserAPIs": [],
      "ssrAPIs": [],
      "pluginFilepath": "/Users/Rurka/dxrs/node_modules/gatsby/dist/internal-plugins/prod-404",
      "packageJson": {
        "name": "prod-404",
        "description": "Internal plugin to detect various flavors of 404 pages and ensure there's a 404.html path created as well to ensure compatability with static hosts",
        "version": "1.0.0",
        "main": "index.js",
        "author": "Kyle Mathews <mathews.kyle@gmail.com>",
        "license": "MIT",
        "dependencies": [],
        "devDependencies": [],
        "peerDependencies": [],
        "optionalDependecies": [],
        "bundledDependecies": []
      },
      "parent": "SOURCE",
      "children": [],
      "internal": {
        "contentDigest": "aab60b8bee0f8be3f0b09b4da03f2ab1",
        "type": "SitePlugin",
        "owner": "internal-data-bridge"
      }
    },
    "84dad27f-1d44-51fc-ac56-4db2e5222995": {
      "resolve": "/Users/Rurka/dxrs/node_modules/gatsby/dist/internal-plugins/query-runner",
      "id": "84dad27f-1d44-51fc-ac56-4db2e5222995",
      "name": "query-runner",
      "version": "1.0.0",
      "pluginOptions": {
        "plugins": []
      },
      "nodeAPIs": [
        "onCreatePage"
      ],
      "browserAPIs": [],
      "ssrAPIs": [],
      "pluginFilepath": "/Users/Rurka/dxrs/node_modules/gatsby/dist/internal-plugins/query-runner",
      "packageJson": {
        "name": "query-runner",
        "description": "Internal plugin for running queries",
        "version": "1.0.0",
        "main": "index.js",
        "author": "",
        "license": "MIT",
        "dependencies": [],
        "devDependencies": [],
        "peerDependencies": [],
        "optionalDependecies": [],
        "bundledDependecies": []
      },
      "parent": "SOURCE",
      "children": [],
      "internal": {
        "contentDigest": "cce06562367649a7cd171568fed0b7c2",
        "type": "SitePlugin",
        "owner": "internal-data-bridge"
      }
    },
    "4303f310-a6d0-5b7c-b8cd-0fc45931d73d": {
      "resolve": "/Users/Rurka/dxrs/node_modules/gatsby-plugin-netlify-cms",
      "id": "4303f310-a6d0-5b7c-b8cd-0fc45931d73d",
      "name": "gatsby-plugin-netlify-cms",
      "version": "3.0.6",
      "pluginOptions": {
        "plugins": []
      },
      "nodeAPIs": [
        "onCreateWebpackConfig"
      ],
      "browserAPIs": [
        "onInitialClientRender"
      ],
      "ssrAPIs": [],
      "pluginFilepath": "/Users/Rurka/dxrs/node_modules/gatsby-plugin-netlify-cms",
      "packageJson": {
        "name": "gatsby-plugin-netlify-cms",
        "description": "A Gatsby plugin which generates the Netlify CMS single page app",
        "version": "3.0.6",
        "main": "index.js",
        "keywords": [
          "gatsby",
          "gatsby-plugin",
          "netlify",
          "netlify-cms",
          "cms"
        ],
        "author": {
          "name": "Shawn Erquhart",
          "email": "shawn@erquh.art"
        },
        "license": "MIT",
        "dependencies": [
          {
            "name": "friendly-errors-webpack-plugin",
            "version": "^1.7.0"
          },
          {
            "name": "html-webpack-exclude-assets-plugin",
            "version": "^0.0.7"
          },
          {
            "name": "html-webpack-plugin",
            "version": "^3.2.0"
          },
          {
            "name": "lodash",
            "version": "^4.17.10"
          },
          {
            "name": "mini-css-extract-plugin",
            "version": "^0.4.1"
          },
          {
            "name": "netlify-identity-widget",
            "version": "^1.4.11"
          },
          {
            "name": "webpack",
            "version": "^4.16.0"
          }
        ],
        "devDependencies": [
          {
            "name": "@babel/cli",
            "version": "^7.0.0"
          },
          {
            "name": "@babel/core",
            "version": "^7.0.0"
          },
          {
            "name": "babel-preset-gatsby-package",
            "version": "^0.1.2"
          },
          {
            "name": "cross-env",
            "version": "^5.1.4"
          },
          {
            "name": "react",
            "version": "^16.4.1"
          },
          {
            "name": "react-dom",
            "version": "^16.4.1"
          }
        ],
        "peerDependencies": [
          {
            "name": "gatsby",
            "version": "^2.0.0-beta.29"
          },
          {
            "name": "netlify-cms",
            "version": "^2.0.6"
          }
        ],
        "optionalDependecies": [],
        "bundledDependecies": []
      },
      "parent": "SOURCE",
      "children": [],
      "internal": {
        "contentDigest": "62564425951fa5610b0006fce4fd0ea0",
        "type": "SitePlugin",
        "owner": "internal-data-bridge"
      }
    },
    "1231ba62-3887-54b5-9281-74f91506bdb0": {
      "resolve": "/Users/Rurka/dxrs/node_modules/gatsby-source-filesystem",
      "id": "1231ba62-3887-54b5-9281-74f91506bdb0",
      "name": "gatsby-source-filesystem",
      "version": "2.0.7",
      "pluginOptions": {
        "plugins": [],
        "path": "/Users/Rurka/dxrs/blog/",
        "name": "markdown-pages"
      },
      "nodeAPIs": [
        "sourceNodes",
        "setFieldsOnGraphQLNodeType"
      ],
      "browserAPIs": [],
      "ssrAPIs": [],
      "pluginFilepath": "/Users/Rurka/dxrs/node_modules/gatsby-source-filesystem",
      "packageJson": {
        "name": "gatsby-source-filesystem",
        "description": "Gatsby plugin which parses files within a directory for further parsing by other plugins",
        "version": "2.0.7",
        "keywords": [
          "gatsby",
          "gatsby-plugin"
        ],
        "author": {
          "name": "Kyle Mathews",
          "email": "mathews.kyle@gmail.com"
        },
        "license": "MIT",
        "dependencies": [
          {
            "name": "@babel/runtime",
            "version": "^7.0.0"
          },
          {
            "name": "better-queue",
            "version": "^3.8.7"
          },
          {
            "name": "bluebird",
            "version": "^3.5.0"
          },
          {
            "name": "chokidar",
            "version": "^1.7.0"
          },
          {
            "name": "file-type",
            "version": "^10.2.0"
          },
          {
            "name": "fs-extra",
            "version": "^5.0.0"
          },
          {
            "name": "got",
            "version": "^7.1.0"
          },
          {
            "name": "md5-file",
            "version": "^3.1.1"
          },
          {
            "name": "mime",
            "version": "^2.2.0"
          },
          {
            "name": "pretty-bytes",
            "version": "^4.0.2"
          },
          {
            "name": "read-chunk",
            "version": "^3.0.0"
          },
          {
            "name": "slash",
            "version": "^1.0.0"
          },
          {
            "name": "valid-url",
            "version": "^1.0.9"
          },
          {
            "name": "xstate",
            "version": "^3.1.0"
          }
        ],
        "devDependencies": [
          {
            "name": "@babel/cli",
            "version": "^7.0.0"
          },
          {
            "name": "@babel/core",
            "version": "^7.0.0"
          },
          {
            "name": "babel-preset-gatsby-package",
            "version": "^0.1.2"
          },
          {
            "name": "cross-env",
            "version": "^5.1.4"
          }
        ],
        "peerDependencies": [
          {
            "name": "gatsby",
            "version": ">2.0.0-alpha"
          }
        ],
        "optionalDependecies": [],
        "bundledDependecies": []
      },
      "parent": "SOURCE",
      "children": [],
      "internal": {
        "contentDigest": "bd703daa2329fe72f144c9d88fd4852e",
        "type": "SitePlugin",
        "owner": "internal-data-bridge"
      }
    },
    "9f28d07a-37b6-51d1-b2d0-5071b57d6dd2": {
      "resolve": "/Users/Rurka/dxrs/node_modules/gatsby-transformer-remark",
      "id": "9f28d07a-37b6-51d1-b2d0-5071b57d6dd2",
      "name": "gatsby-transformer-remark",
      "version": "2.1.11",
      "pluginOptions": {
        "plugins": []
      },
      "nodeAPIs": [
        "onCreateNode",
        "setFieldsOnGraphQLNodeType"
      ],
      "browserAPIs": [],
      "ssrAPIs": [],
      "pluginFilepath": "/Users/Rurka/dxrs/node_modules/gatsby-transformer-remark",
      "packageJson": {
        "name": "gatsby-transformer-remark",
        "description": "Gatsby transformer plugin for Markdown using the Remark library and ecosystem",
        "version": "2.1.11",
        "keywords": [
          "gatsby",
          "gatsby-plugin",
          "markdown",
          "remark"
        ],
        "author": {
          "name": "Kyle Mathews",
          "email": "mathews.kyle@gmail.com"
        },
        "license": "MIT",
        "dependencies": [
          {
            "name": "@babel/runtime",
            "version": "^7.0.0"
          },
          {
            "name": "bluebird",
            "version": "^3.5.0"
          },
          {
            "name": "gray-matter",
            "version": "^4.0.0"
          },
          {
            "name": "hast-util-raw",
            "version": "^4.0.0"
          },
          {
            "name": "hast-util-to-html",
            "version": "^4.0.0"
          },
          {
            "name": "lodash",
            "version": "^4.17.10"
          },
          {
            "name": "mdast-util-to-hast",
            "version": "^3.0.0"
          },
          {
            "name": "mdast-util-toc",
            "version": "^2.0.1"
          },
          {
            "name": "remark",
            "version": "^9.0.0"
          },
          {
            "name": "remark-parse",
            "version": "^5.0.0"
          },
          {
            "name": "remark-retext",
            "version": "^3.1.0"
          },
          {
            "name": "remark-stringify",
            "version": "^5.0.0"
          },
          {
            "name": "retext-english",
            "version": "^3.0.0"
          },
          {
            "name": "sanitize-html",
            "version": "^1.18.2"
          },
          {
            "name": "underscore.string",
            "version": "^3.3.4"
          },
          {
            "name": "unified",
            "version": "^6.1.5"
          },
          {
            "name": "unist-util-remove-position",
            "version": "^1.1.2"
          },
          {
            "name": "unist-util-select",
            "version": "^1.5.0"
          },
          {
            "name": "unist-util-visit",
            "version": "^1.3.0"
          }
        ],
        "devDependencies": [
          {
            "name": "@babel/cli",
            "version": "^7.0.0"
          },
          {
            "name": "@babel/core",
            "version": "^7.0.0"
          },
          {
            "name": "babel-preset-gatsby-package",
            "version": "^0.1.2"
          },
          {
            "name": "cross-env",
            "version": "^5.1.4"
          }
        ],
        "peerDependencies": [
          {
            "name": "gatsby",
            "version": "^2.0.33"
          }
        ],
        "optionalDependecies": [],
        "bundledDependecies": []
      },
      "parent": "SOURCE",
      "children": [],
      "internal": {
        "contentDigest": "40a0af3bb6b066ffee9ffa32a6af14a9",
        "type": "SitePlugin",
        "owner": "internal-data-bridge"
      }
    },
    "7374ebf2-d961-52ee-92a2-c25e7cb387a9": {
      "resolve": "/Users/Rurka/dxrs",
      "id": "7374ebf2-d961-52ee-92a2-c25e7cb387a9",
      "name": "default-site-plugin",
      "version": "c9513145044e9784568d9e07f33976f1",
      "pluginOptions": {
        "plugins": []
      },
      "nodeAPIs": [
        "createPages"
      ],
      "browserAPIs": [],
      "ssrAPIs": [],
      "pluginFilepath": "/Users/Rurka/dxrs",
      "packageJson": {
        "name": "gatsby-starter-hello-world",
        "description": "Gatsby hello world starter",
        "license": "MIT",
        "dependencies": [
          {
            "name": "gatsby",
            "version": "^2.0.33"
          },
          {
            "name": "gatsby-plugin-netlify-cms",
            "version": "^3.0.6"
          },
          {
            "name": "gatsby-source-filesystem",
            "version": "^2.0.7"
          },
          {
            "name": "gatsby-transformer-remark",
            "version": "^2.1.11"
          },
          {
            "name": "netlify-cms",
            "version": "^2.1.3"
          },
          {
            "name": "react",
            "version": "^16.5.1"
          },
          {
            "name": "react-dom",
            "version": "^16.5.1"
          }
        ],
        "devDependencies": [],
        "peerDependencies": [],
        "optionalDependecies": [],
        "bundledDependecies": []
      },
      "parent": "SOURCE",
      "children": [],
      "internal": {
        "contentDigest": "3d676d7279cbd8b2b5560a1627855ecb",
        "type": "SitePlugin",
        "owner": "internal-data-bridge"
      }
    },
    "3664a81b-e58f-5706-a248-c78b6bd4a6a2": {
      "resolve": "/Users/Rurka/dxrs/node_modules/gatsby-plugin-page-creator",
      "id": "3664a81b-e58f-5706-a248-c78b6bd4a6a2",
      "name": "gatsby-plugin-page-creator",
      "version": "2.0.3",
      "pluginOptions": {
        "plugins": [],
        "path": "/Users/Rurka/dxrs/src/pages",
        "pathCheck": false
      },
      "nodeAPIs": [
        "createPagesStatefully"
      ],
      "browserAPIs": [],
      "ssrAPIs": [],
      "pluginFilepath": "/Users/Rurka/dxrs/node_modules/gatsby-plugin-page-creator",
      "packageJson": {
        "name": "gatsby-plugin-page-creator",
        "description": "Gatsby plugin that automatically creates pages from React components in specified directories",
        "version": "2.0.3",
        "main": "index.js",
        "keywords": [
          "gatsby",
          "gatsby-plugin"
        ],
        "author": {
          "name": "Kyle Mathews",
          "email": "mathews.kyle@gmail.com"
        },
        "license": "MIT",
        "dependencies": [
          {
            "name": "@babel/runtime",
            "version": "^7.0.0"
          },
          {
            "name": "bluebird",
            "version": "^3.5.0"
          },
          {
            "name": "chokidar",
            "version": "^1.7.0"
          },
          {
            "name": "fs-exists-cached",
            "version": "^1.0.0"
          },
          {
            "name": "glob",
            "version": "^7.1.1"
          },
          {
            "name": "lodash",
            "version": "^4.17.10"
          },
          {
            "name": "micromatch",
            "version": "^3.1.10"
          },
          {
            "name": "parse-filepath",
            "version": "^1.0.1"
          },
          {
            "name": "slash",
            "version": "^1.0.0"
          }
        ],
        "devDependencies": [
          {
            "name": "@babel/cli",
            "version": "^7.0.0"
          },
          {
            "name": "@babel/core",
            "version": "^7.0.0"
          },
          {
            "name": "babel-preset-gatsby-package",
            "version": "^0.1.2"
          },
          {
            "name": "cross-env",
            "version": "^5.0.5"
          }
        ],
        "peerDependencies": [
          {
            "name": "gatsby",
            "version": ">2.0.0-alpha"
          }
        ],
        "optionalDependecies": [],
        "bundledDependecies": []
      },
      "parent": "SOURCE",
      "children": [],
      "internal": {
        "contentDigest": "2d283e304241fbcdf983e1586f10ad2c",
        "type": "SitePlugin",
        "owner": "internal-data-bridge"
      }
    },
    "Site": {
      "siteMetadata": {
        "title": "My Homepage",
        "description": "This is where I write my thoughts."
      },
      "port": "8000",
      "host": "localhost",
      "pathPrefix": "",
      "polyfill": true,
      "buildTime": "2018-11-06T07:48:56.628Z",
      "id": "Site",
      "parent": "SOURCE",
      "children": [],
      "internal": {
        "contentDigest": "5caca3d83904643194a4da1054129e84",
        "type": "Site",
        "owner": "internal-data-bridge"
      }
    },
    "19881883-9ea0-592f-925e-e79faa6f1a7f": {
      "id": "19881883-9ea0-592f-925e-e79faa6f1a7f",
      "children": [],
      "parent": "___SOURCE___",
      "internal": {
        "contentDigest": "f782acd542a18cf79dce8ce5969528e8",
        "type": "Directory",
        "description": "Directory \"blog\"",
        "owner": "gatsby-source-filesystem"
      },
      "sourceInstanceName": "markdown-pages",
      "absolutePath": "/Users/Rurka/dxrs/blog/",
      "relativePath": "",
      "extension": "",
      "size": 170,
      "prettySize": "170 B",
      "modifiedTime": "2018-11-06T07:44:42.000Z",
      "accessTime": "2018-11-06T07:49:01.000Z",
      "changeTime": "2018-11-06T07:44:42.000Z",
      "birthTime": "2018-11-06T04:10:23.000Z",
      "root": "/",
      "dir": "/Users/Rurka/dxrs",
      "base": "blog",
      "ext": "",
      "name": "blog",
      "relativeDirectory": "..",
      "dev": 16777220,
      "mode": 16877,
      "nlink": 5,
      "uid": 501,
      "gid": 20,
      "rdev": 0,
      "blksize": 4096,
      "ino": 175945237,
      "blocks": 0,
      "atimeMs": 1541490541000,
      "mtimeMs": 1541490282000,
      "ctimeMs": 1541490282000,
      "birthtimeMs": 1541477423000,
      "atime": "2018-11-06T07:49:01.000Z",
      "mtime": "2018-11-06T07:44:42.000Z",
      "ctime": "2018-11-06T07:44:42.000Z",
      "birthtime": "2018-11-06T04:10:23.000Z"
    },
    "b0ec4fc6-518a-5e77-bcbb-72856af2b291": {
      "id": "b0ec4fc6-518a-5e77-bcbb-72856af2b291",
      "children": [
        "c7f6b30d-28c9-5319-a895-fd86269356c1"
      ],
      "parent": "___SOURCE___",
      "internal": {
        "contentDigest": "03a019a0c694df6af24d324e7a98c5ec",
        "type": "File",
        "mediaType": "text/markdown",
        "description": "File \"blog/test-1.md\"",
        "owner": "gatsby-source-filesystem"
      },
      "sourceInstanceName": "markdown-pages",
      "absolutePath": "/Users/Rurka/dxrs/blog/test-1.md",
      "relativePath": "test-1.md",
      "extension": "md",
      "size": 129,
      "prettySize": "129 B",
      "modifiedTime": "2018-11-06T07:48:49.000Z",
      "accessTime": "2018-11-06T07:48:49.000Z",
      "changeTime": "2018-11-06T07:48:49.000Z",
      "birthTime": "2018-11-06T04:10:23.000Z",
      "root": "/",
      "dir": "/Users/Rurka/dxrs/blog",
      "base": "test-1.md",
      "ext": ".md",
      "name": "test-1",
      "relativeDirectory": "",
      "dev": 16777220,
      "mode": 33188,
      "nlink": 1,
      "uid": 501,
      "gid": 20,
      "rdev": 0,
      "blksize": 4096,
      "ino": 175945238,
      "blocks": 8,
      "atimeMs": 1541490529000,
      "mtimeMs": 1541490529000,
      "ctimeMs": 1541490529000,
      "birthtimeMs": 1541477423000,
      "atime": "2018-11-06T07:48:49.000Z",
      "mtime": "2018-11-06T07:48:49.000Z",
      "ctime": "2018-11-06T07:48:49.000Z",
      "birthtime": "2018-11-06T04:10:23.000Z"
    },
    "63c06d9e-d7cf-53fa-b4a2-4b13665fcf7f": {
      "id": "63c06d9e-d7cf-53fa-b4a2-4b13665fcf7f",
      "children": [
        "49a9f2a0-4aaa-5cf9-a023-2c49a23636d8"
      ],
      "parent": "___SOURCE___",
      "internal": {
        "contentDigest": "c124057922f8b87130ffcd7063168f20",
        "type": "File",
        "mediaType": "text/markdown",
        "description": "File \"blog/test-2.md\"",
        "owner": "gatsby-source-filesystem"
      },
      "sourceInstanceName": "markdown-pages",
      "absolutePath": "/Users/Rurka/dxrs/blog/test-2.md",
      "relativePath": "test-2.md",
      "extension": "md",
      "size": 179,
      "prettySize": "179 B",
      "modifiedTime": "2018-11-06T07:48:29.000Z",
      "accessTime": "2018-11-06T07:48:29.000Z",
      "changeTime": "2018-11-06T07:48:29.000Z",
      "birthTime": "2018-11-06T04:10:23.000Z",
      "root": "/",
      "dir": "/Users/Rurka/dxrs/blog",
      "base": "test-2.md",
      "ext": ".md",
      "name": "test-2",
      "relativeDirectory": "",
      "dev": 16777220,
      "mode": 33188,
      "nlink": 1,
      "uid": 501,
      "gid": 20,
      "rdev": 0,
      "blksize": 4096,
      "ino": 175945239,
      "blocks": 8,
      "atimeMs": 1541490509000,
      "mtimeMs": 1541490509000,
      "ctimeMs": 1541490509000,
      "birthtimeMs": 1541477423000,
      "atime": "2018-11-06T07:48:29.000Z",
      "mtime": "2018-11-06T07:48:29.000Z",
      "ctime": "2018-11-06T07:48:29.000Z",
      "birthtime": "2018-11-06T04:10:23.000Z"
    },
    "4d08a988-8839-5b5a-9f67-603d5d46ba0a": {
      "id": "4d08a988-8839-5b5a-9f67-603d5d46ba0a",
      "children": [
        "8bf6e096-e795-5edb-93f7-8ee1de97436b"
      ],
      "parent": "___SOURCE___",
      "internal": {
        "contentDigest": "8e534e11b3685f71abacfe6efaab6b77",
        "type": "File",
        "mediaType": "text/markdown",
        "description": "File \"blog/test-3.md\"",
        "owner": "gatsby-source-filesystem"
      },
      "sourceInstanceName": "markdown-pages",
      "absolutePath": "/Users/Rurka/dxrs/blog/test-3.md",
      "relativePath": "test-3.md",
      "extension": "md",
      "size": 138,
      "prettySize": "138 B",
      "modifiedTime": "2018-11-06T07:48:46.000Z",
      "accessTime": "2018-11-06T07:48:46.000Z",
      "changeTime": "2018-11-06T07:48:46.000Z",
      "birthTime": "2018-11-06T07:44:42.000Z",
      "root": "/",
      "dir": "/Users/Rurka/dxrs/blog",
      "base": "test-3.md",
      "ext": ".md",
      "name": "test-3",
      "relativeDirectory": "",
      "dev": 16777220,
      "mode": 33188,
      "nlink": 1,
      "uid": 501,
      "gid": 20,
      "rdev": 0,
      "blksize": 4096,
      "ino": 175963736,
      "blocks": 8,
      "atimeMs": 1541490526000,
      "mtimeMs": 1541490526000,
      "ctimeMs": 1541490526000,
      "birthtimeMs": 1541490282000,
      "atime": "2018-11-06T07:48:46.000Z",
      "mtime": "2018-11-06T07:48:46.000Z",
      "ctime": "2018-11-06T07:48:46.000Z",
      "birthtime": "2018-11-06T07:44:42.000Z"
    },
    "49a9f2a0-4aaa-5cf9-a023-2c49a23636d8": {
      "id": "49a9f2a0-4aaa-5cf9-a023-2c49a23636d8",
      "children": [],
      "parent": "63c06d9e-d7cf-53fa-b4a2-4b13665fcf7f",
      "internal": {
        "content": "Another award winning post by Michael Rurka. Wow. He's so handsome. Good job! Nobel prize!!\n",
        "type": "MarkdownRemark",
        "contentDigest": "01b4baff1b0a8d59e0e110b621314e55",
        "owner": "gatsby-transformer-remark"
      },
      "frontmatter": {
        "title": "Test 2",
        "path": "/test-2",
        "city": "San Francisco",
        "date": "2018-11-06T04:07:11.555Z",
        "_PARENT": "63c06d9e-d7cf-53fa-b4a2-4b13665fcf7f"
      },
      "excerpt": "",
      "rawMarkdownBody": "Another award winning post by Michael Rurka. Wow. He's so handsome. Good job! Nobel prize!!\n",
      "fileAbsolutePath": "/Users/Rurka/dxrs/blog/test-2.md"
    },
    "c7f6b30d-28c9-5319-a895-fd86269356c1": {
      "id": "c7f6b30d-28c9-5319-a895-fd86269356c1",
      "children": [],
      "parent": "b0ec4fc6-518a-5e77-bcbb-72856af2b291",
      "internal": {
        "content": "Awesome content. Amazing blog. Wow. Much wizdom.\n",
        "type": "MarkdownRemark",
        "contentDigest": "3324f33965be07ad2c1e8346d3ee222d",
        "owner": "gatsby-transformer-remark"
      },
      "frontmatter": {
        "title": "Test 1",
        "path": "/apple",
        "city": "Toronto",
        "date": "2018-11-06T03:40:20.403Z",
        "_PARENT": "b0ec4fc6-518a-5e77-bcbb-72856af2b291"
      },
      "excerpt": "",
      "rawMarkdownBody": "Awesome content. Amazing blog. Wow. Much wizdom.\n",
      "fileAbsolutePath": "/Users/Rurka/dxrs/blog/test-1.md"
    },
    "8bf6e096-e795-5edb-93f7-8ee1de97436b": {
      "id": "8bf6e096-e795-5edb-93f7-8ee1de97436b",
      "children": [],
      "parent": "4d08a988-8839-5b5a-9f67-603d5d46ba0a",
      "internal": {
        "content": "Wow, amazing article. Another best seller book. wow.\n",
        "type": "MarkdownRemark",
        "contentDigest": "5d89454f96eb01d3502f3319815d5f16",
        "owner": "gatsby-transformer-remark"
      },
      "frontmatter": {
        "title": "Test 3",
        "path": "/test-3",
        "city": "Fredericton",
        "date": "2018-11-06T07:42:29.956Z",
        "_PARENT": "4d08a988-8839-5b5a-9f67-603d5d46ba0a"
      },
      "excerpt": "",
      "rawMarkdownBody": "Wow, amazing article. Another best seller book. wow.\n",
      "fileAbsolutePath": "/Users/Rurka/dxrs/blog/test-3.md"
    },
    "SitePage /test-3": {
      "jsonName": "test-3-05d",
      "internalComponentName": "ComponentTest3",
      "path": "/test-3",
      "component": "/Users/Rurka/dxrs/src/templates/blogTemplate.js",
      "componentChunkName": "component---src-templates-blog-template-js",
      "context": {},
      "pluginCreator___NODE": "7374ebf2-d961-52ee-92a2-c25e7cb387a9",
      "pluginCreatorId": "7374ebf2-d961-52ee-92a2-c25e7cb387a9",
      "componentPath": "/Users/Rurka/dxrs/src/templates/blogTemplate.js",
      "id": "SitePage /test-3",
      "parent": "SOURCE",
      "children": [],
      "internal": {
        "type": "SitePage",
        "contentDigest": "d594b6ab5c2765731100e3ef43dae4bc",
        "description": "7374ebf2-d961-52ee-92a2-c25e7cb387a9",
        "owner": "internal-data-bridge"
      }
    },
    "SitePage /test-2": {
      "jsonName": "test-2-aaf",
      "internalComponentName": "ComponentTest2",
      "path": "/test-2",
      "component": "/Users/Rurka/dxrs/src/templates/blogTemplate.js",
      "componentChunkName": "component---src-templates-blog-template-js",
      "context": {},
      "pluginCreator___NODE": "7374ebf2-d961-52ee-92a2-c25e7cb387a9",
      "pluginCreatorId": "7374ebf2-d961-52ee-92a2-c25e7cb387a9",
      "componentPath": "/Users/Rurka/dxrs/src/templates/blogTemplate.js",
      "id": "SitePage /test-2",
      "parent": "SOURCE",
      "children": [],
      "internal": {
        "type": "SitePage",
        "contentDigest": "32330fd1b5f53b9488b60ecfebcb78ac",
        "description": "7374ebf2-d961-52ee-92a2-c25e7cb387a9",
        "owner": "internal-data-bridge"
      }
    },
    "SitePage /apple": {
      "jsonName": "apple-a69",
      "internalComponentName": "ComponentApple",
      "path": "/apple",
      "component": "/Users/Rurka/dxrs/src/templates/blogTemplate.js",
      "componentChunkName": "component---src-templates-blog-template-js",
      "context": {},
      "pluginCreator___NODE": "7374ebf2-d961-52ee-92a2-c25e7cb387a9",
      "pluginCreatorId": "7374ebf2-d961-52ee-92a2-c25e7cb387a9",
      "componentPath": "/Users/Rurka/dxrs/src/templates/blogTemplate.js",
      "id": "SitePage /apple",
      "parent": "SOURCE",
      "children": [],
      "internal": {
        "type": "SitePage",
        "contentDigest": "fec4a11b0c2c5b38be648820cc2c905c",
        "description": "7374ebf2-d961-52ee-92a2-c25e7cb387a9",
        "owner": "internal-data-bridge"
      }
    },
    "SitePage /": {
      "jsonName": "index",
      "internalComponentName": "ComponentIndex",
      "path": "/",
      "component": "/Users/Rurka/dxrs/src/pages/index.js",
      "componentChunkName": "component---src-pages-index-js",
      "context": {},
      "pluginCreator___NODE": "3664a81b-e58f-5706-a248-c78b6bd4a6a2",
      "pluginCreatorId": "3664a81b-e58f-5706-a248-c78b6bd4a6a2",
      "componentPath": "/Users/Rurka/dxrs/src/pages/index.js",
      "id": "SitePage /",
      "parent": "SOURCE",
      "children": [],
      "internal": {
        "type": "SitePage",
        "contentDigest": "9a5a1270235447b6e7bc4019c84f50e0",
        "description": "3664a81b-e58f-5706-a248-c78b6bd4a6a2",
        "owner": "internal-data-bridge"
      }
    }
  },
  "status": {
    "plugins": {},
    "PLUGINS_HASH": "8cad86038e1188c12f227fbfbbd31eb4"
  },
  "componentDataDependencies": {
    "nodes": {
      "d48d1c52-fe48-53cb-8f08-aa4b47dde5a5": [
        "/"
      ],
      "7374ebf2-d961-52ee-92a2-c25e7cb387a9": [
        "/"
      ],
      "3664a81b-e58f-5706-a248-c78b6bd4a6a2": [
        "/"
      ],
      "8bf6e096-e795-5edb-93f7-8ee1de97436b": [
        "/test-3"
      ],
      "49a9f2a0-4aaa-5cf9-a023-2c49a23636d8": [
        "/test-2"
      ],
      "c7f6b30d-28c9-5319-a895-fd86269356c1": [
        "/apple"
      ]
    },
    "connections": {
      "MarkdownRemark": [
        null,
        "/",
        null
      ],
      "SitePage": [
        null,
        null
      ]
    }
  },
  "jsonDataPaths": {
    "dev-404-page-5f9": "920/path---dev-404-page-5-f-9-fab-NZuapzHg3X9TaN1iIixfv1W23E",
    "index": "139/path---index-6a9-9rltADDbeGFTTMg7tBkk0ysiOI",
    "test-2-282": "763/path---test-2-282-8c9-YgV6PMucCfm5UqFLltIiArHr58",
    "apple-1f3": "882/path---apple-1-f-3-e0b-YgV6PMucCfm5UqFLltIiArHr58",
    "test-3-2b6": "879/path---test-3-2-b-6-e03-YgV6PMucCfm5UqFLltIiArHr58",
    "test-3-05d": "823/path---test-3-05-d-143-xy2Jh47jbZYGGnY2mh2ATX7lIK0",
    "apple-a69": "491/path---apple-a-69-3b7-1lLHY5Tbn6PdISK1phow3AEbo",
    "test-2-aaf": "721/path---test-2-aaf-80c-oEBK71KN2JLejtRNjqge4Gus"
  },
  "components": {
    "/Users/Rurka/dxrs/src/templates/blogTemplate.js": {
      "query": "query usersRurkaDxrsSrcTemplatesBlogTemplateJs1579142440(\n  $path: String!\n) {\n  markdownRemark(frontmatter: {path: {eq: $path}}) {\n    html\n    frontmatter {\n      date(formatString: \"MMMM DD, YYYY\")\n      path\n      title\n    }\n  }\n}\n",
      "componentPath": "/Users/Rurka/dxrs/src/templates/blogTemplate.js"
    },
    "/Users/Rurka/dxrs/.cache/dev-404-page.js": {
      "query": "",
      "componentPath": "/Users/Rurka/dxrs/.cache/dev-404-page.js"
    },
    "/Users/Rurka/dxrs/src/pages/index.js": {
      "query": "query usersRurkaDxrsSrcPagesIndexJs3473231669 {\n  allMarkdownRemark(sort: {order: DESC, fields: [frontmatter___date]}) {\n    edges {\n      node {\n        id\n        excerpt(pruneLength: 250)\n        frontmatter {\n          date(formatString: \"MMMM DD, YYYY\")\n          path\n          title\n        }\n      }\n    }\n  }\n}\n",
      "componentPath": "/Users/Rurka/dxrs/src/pages/index.js"
    }
  },
  "staticQueryComponents": {}
}